finpricer/__init__.py
finpricer/bond.py
finpricer/bond_future.py
finpricer/bond_future_us.py
finpricer/credit_default_swap.py
finpricer/cross_currency_cds.py
finpricer/cross_currency_swap.py
finpricer/interest_rate_swap.py
finpricer-0.1.0.dist-info/licenses/LICENSE
finpricer-0.1.0.dist-info/METADATA
finpricer-0.1.0.dist-info/WHEEL
finpricer-0.1.0.dist-info/top_level.txt
finpricer-0.1.0.dist-info/RECORD
